__init__.py
ssmc.py
ssmc-1.3.0.data/data/requirements-dev.txt
ssmc-1.3.0.dist-info/LICENCE
ssmc-1.3.0.dist-info/METADATA
ssmc-1.3.0.dist-info/WHEEL
ssmc-1.3.0.dist-info/top_level.txt
ssmc-1.3.0.dist-info/RECORD
