Metadata-Version: 2.1
Name: ssmc
Version: 1.3.0
Summary: Sakura Secure Mobile Connect API tool
Home-page: https://github.com/hitsumabushi/python-sakura-secure-mobile-connect
Author: hitsumabushi
Author-email: hitsumabushi.org@gmail.com
License: UNKNOWN
Project-URL: Bug Reports, https://github.com/hitsumabushi/python-sakura-secure-mobile-connect/issues
Project-URL: Source, https://github.com/hitsumabushi/python-sakura-secure-mobile-connect
Keywords: SAKURA Cloud SIM SakuraSecureMobileConnect SSMC
Platform: UNKNOWN
Classifier: Development Status :: 5 - Production/Stable
Classifier: Intended Audience :: Developers
Classifier: License :: OSI Approved :: Apache Software License
Classifier: Programming Language :: Python :: 3
Classifier: Programming Language :: Python :: 3.6
Requires-Dist: certifi
Requires-Dist: chardet
Requires-Dist: idna
Requires-Dist: requests
Requires-Dist: urllib3
Provides-Extra: dev
Requires-Dist: sphinx ; extra == 'dev'
Requires-Dist: check-manifest ; extra == 'dev'
